ifcfm/__init__.py
ifcfm/__main__.py
ifcfm/basic.py
ifcfm/cobie24.py
ifcfm/cobie24legacy.py
ifcfm-0.8.3.dist-info/METADATA
ifcfm-0.8.3.dist-info/WHEEL
ifcfm-0.8.3.dist-info/top_level.txt
ifcfm-0.8.3.dist-info/RECORD
