Metadata-Version: 2.4
Name: ifcfm
Version: 0.8.3
Summary: Extract data from IFC following facility management standards
Author-email: Dion Moult <dion@thinkmoult.com>
Project-URL: Homepage, http://ifcopenshell.org
Project-URL: Documentation, https://docs.ifcopenshell.org
Project-URL: Issues, https://github.com/IfcOpenShell/IfcOpenShell/issues
Keywords: IFC,FM,BIM
Classifier: Programming Language :: Python :: 3
Classifier: License :: OSI Approved :: GNU Lesser General Public License v3 or later (LGPLv3+)
Requires-Dist: ifcopenshell
Requires-Dist: openpyxl
Requires-Dist: odfpy
Requires-Dist: pandas
